sua.py
sua-1.1.5.1.dist-info/METADATA
sua-1.1.5.1.dist-info/WHEEL
sua-1.1.5.1.dist-info/top_level.txt
sua-1.1.5.1.dist-info/RECORD
