Metadata-Version: 2.1
Name: sua
Version: 1.1.5.1
Summary: Stochastic Unified Assistant (a.k.a SUA).
Home-page: https://https://github.com/kingsman1960/Sua
Author: Youngwon Cho
Author-email: youngwon.cho@tum.de
License: MIT
Platform: UNKNOWN
Requires-Python: >=3.7
Requires-Dist: numpy (>=1.21.6)
Requires-Dist: matplotlib (>=3.4.1)
Requires-Dist: datetime
Requires-Dist: empyrical (>=0.5.5)
Requires-Dist: quantstats (>=0.0.59)
Requires-Dist: ipython
Requires-Dist: fpdf (>=1.7.2)
Requires-Dist: pyportfolioopt (>=1.5.2)
Requires-Dist: darts (>=0.13.1)
Requires-Dist: prophet (>=1.1.1)
Requires-Dist: pandas (>=1.3.5)
Requires-Dist: cvxpy (>=1.2.2)
Requires-Dist: scikit-learn (>=1.0.2)
Requires-Dist: streamlit (>=1.15.0)
